code_aimpetus/__init__.py
code_aimpetus/__main__.py
code_aimpetus/celery.py
code_aimpetus/common_options.py
code_aimpetus/settings.py
code_aimpetus/gh/__init__.py
code_aimpetus/gh/repo.py
code_aimpetus/gh/utility.py
code_aimpetus/gh/issues/__init__.py
code_aimpetus/gh/issues/check_templates.py
code_aimpetus/gh/issues/close.py
code_aimpetus/gh/issues/get.py
code_aimpetus/gh/issues/list.py
code_aimpetus/gh/pull_requests/__init__.py
code_aimpetus/gh/pull_requests/list.py
code_aimpetus-0.2.0.dist-info/METADATA
code_aimpetus-0.2.0.dist-info/WHEEL
code_aimpetus-0.2.0.dist-info/entry_points.txt
code_aimpetus-0.2.0.dist-info/licenses/LICENSE
code_aimpetus-0.2.0.dist-info/RECORD
